Compiled from "GLDynamicLibraryBundleInfo.java"
public abstract class jogamp.opengl.GLDynamicLibraryBundleInfo implements com.jogamp.common.os.DynamicLibraryBundleInfo {
  protected jogamp.opengl.GLDynamicLibraryBundleInfo();
    Code:
       0: aload_0
       1: invokespecial #1                  // Method java/lang/Object."<init>":()V
       4: return

  public final boolean shallLinkGlobal();
    Code:
       0: iconst_1
       1: ireturn

  public boolean shallLookupGlobal();
    Code:
       0: iconst_0
       1: ireturn

  public final com.jogamp.common.util.RunnableExecutor getLibLoaderExecutor();
    Code:
       0: invokestatic  #2                  // Method com/jogamp/common/os/DynamicLibraryBundle.getDefaultRunnableExecutor:()Lcom/jogamp/common/util/RunnableExecutor;
       3: areturn
}
